{
  "$id": "",
  "type": "object",
  "properties": {
    "ilaId": {
      "type": "string",
      "minLength": 1
    },
    "token": {
      "type": "string",
      "minLength": 10
    },
    "cid": {
      "type": "string",
      "minLength": 1
    },
    "def": {
      "type": "object",
      "properties": {}
    },
    "payload": {
      "type": "object",
      "properties": {}
    },
    "valid": {
      "type": "boolean",
      "default": false
    }
  },
  "required": [
    "ilaId",
    "token",
    "cid",
    "def",
    "payload"
  ],
  "additionalProperties": true
}
